keyvalue_sqlite/__init__.py
keyvalue_sqlite/keyvalue_sqlite.py
keyvalue_sqlite-1.0.7.dist-info/LICENSE
keyvalue_sqlite-1.0.7.dist-info/METADATA
keyvalue_sqlite-1.0.7.dist-info/WHEEL
keyvalue_sqlite-1.0.7.dist-info/top_level.txt
keyvalue_sqlite-1.0.7.dist-info/RECORD
