Metadata-Version: 2.1
Name: keyvalue-sqlite
Version: 1.0.7
Summary: Super simple keyvalue store for python, backed by sqlite.
Home-page: https://github.com/zackees/keyvalue_sqlite
Author: Zach Vorhies
Author-email: dont@email.me
License: MIT
Classifier: License :: OSI Approved :: MIT License
Classifier: Programming Language :: Python :: 3
Classifier: Programming Language :: Python :: 3.7
Requires-Python: >=3.6.0
License-File: LICENSE
